
mypykits
