Metadata-Version: 2.1
Name: mypykits
Version: 1.0.1
Summary: This is a PyPackage for web spider.
Home-page: 
Author: kinney
Author-email: 1409224614@qq.com
License: MIT
License-File: LICENSE.txt
